Workbook

Sheet Diagrama ER (corregido)

Sheet Inventario Modelo Lógico (corre
A1: Tablas resultantes del Diccionario Genérico (Modelo Lógico)
A2: # | B2: Tabla | C2: Descripción Tabla | D2: Observaciones
A3: 1 | B3: usuario | C3: Persona registrada en la plataforma que interactúa con la red social. | D3: Origen: Entidad Usuario | PK: id_usuario | FK: id_rol, id_tipo_usuario | UK: nombre_usuario, correo
A4: =A3+1 -> 2 | B4: rol | C4: Clasifica a los usuarios según sus permisos y nivel de acceso dentro del sistema. | D4: Origen: Entidad Rol | PK: id_rol | UK: nombre_rol
A5: =A4+1 -> 3 | B5: tipo_usuario | C5: Clasificación académica o profesional del usuario con fines estadísticos. | D5: Origen: Entidad TipoUsuario | PK: id_tipo_usuario | UK: nombre_tipo
A6: =A5+1 -> 4 | B6: perfil | C6: Extensión de la información del usuario que almacena intereses, habilidades y datos adicionales en formato JSONB. | D6: Origen: Entidad Perfil (débil) | PK: id_perfil | FK: id_usuario | UK: id_usuario
A7: =A6+1 -> 5 | B7: interes | C7: Catálogo de intereses personales (fotografía, videojuegos, lectura, etc.) que los usuarios pueden asociar a su cuenta. | D7: Origen: Entidad Interes | PK: id_interes | UK: nombre_interes
A8: =A7+1 -> 6 | B8: habilidad | C8: Catálogo de habilidades (programación, diseño gráfico, etc.) que los usuarios pueden declarar en su cuenta. | D8: Origen: Entidad Habilidad | PK: id_habilidad | UK: nombre_habilidad
A9: =A8+1 -> 7 | B9: publicacion | C9: Contenido compartido por un usuario en el muro de la red social. | D9: Origen: Entidad Publicacion | PK: id_publicacion | FK: id_usuario
A10: =A9+1 -> 8 | B10: comentario | C10: Respuesta o reacción escrita que un usuario realiza sobre una publicación específica. | D10: Origen: Entidad Comentario (débil) | PK: id_comentario | FK: id_publicacion, id_usuario, id_comentario_padre
A11: =A10+1 -> 9 | B11: grupo | C11: Espacio colaborativo creado para reunir usuarios con intereses académicos, deportivos o de ocio en común. | D11: Origen: Entidad Grupo | PK: id_grupo | FK: id_usuario_creador
A12: =A11+1 -> 10 | B12: tipo_servicio | C12: Catálogo predefinido que clasifica los servicios ofrecidos (tutorías, reparaciones, asesorías, etc.). | D12: Origen: Entidad TipoServicio | PK: id_tipo_servicio | UK: nombre_tipo
A13: =A12+1 -> 11 | B13: servicio | C13: Oferta concreta que un usuario publica para brindar un servicio a otros, con precio y descripción. | D13: Origen: Entidad Servicio | PK: id_servicio | FK: id_tipo_servicio, id_usuario
A14: =A13+1 -> 12 | B14: tipo_producto | C14: Catálogo predefinido que clasifica los productos en venta (libros, tecnología, ropa, etc.). | D14: Origen: Entidad TipoProducto | PK: id_tipo_producto | UK: nombre_tipo
A15: =A14+1 -> 13 | B15: producto | C15: Artículo físico o digital que un usuario publica para vender o adquirir dentro de la plataforma. | D15: Origen: Entidad Producto | PK: id_producto | FK: id_tipo_producto, id_usuario
... A33: =A32+1 -> 31 | B33: venta_evento | C33: Detalle de los eventos incluidos en cada venta (por ejemplo, entradas), con la cantidad y el precio unitario. | D33: Origen: Relación M:N Venta — incluye — Evento | PK: id_venta_evento | FK: id_venta, id_evento | UK compuesta: (id_venta, id_evento)

Sheet Tipos de Dato
A1: Tipos de Datos - Tabla Comparativa
A2: # | B2: Tipo de Dato Genérico | C2: Tipos de Dato - PosgreSQL | D2: DOMINIO | E2: BYTES | F2: Observaciones
A3: 1 | B3: AUTOINCREMENTABLE | C3: SERIAL (equivale a INTEGER con secuencia; alternativa: INTEGER GENERATED ALWAYS AS IDENTITY) | D3: 1 a 2,147,483,647 | E3: 4 | F3: Usado en todas las llaves primarias. Si se espera más de 2 mil millones de filas se usa BIGSERIAL (8 bytes).
A4: =A3+1 -> 2 | B4: UUID | C4: UUID | D4: Se representa como una cadena de 32 dígitos hexadecimales | E4: 16 | F4: Identificador universal. No se usa en este modelo; se deja como referencia.
A5: =A4+1 -> 3 | B5: ENTERO | C5: INTEGER | D5: -2,147,483,648 a +2,147,483,647 | E5: 4 | F5: Llaves foráneas y cantidades. Alternativas: SMALLINT (2 bytes) y BIGINT (8 bytes). En PostgreSQL el INTEGER no usa ancho de visualización; el tamaño 11 del diccionario se conserva de la tarea 2.
A6: =A5+1 -> 4 | B6: DECIMAL | C6: NUMERIC(p,s) | D6: NUMERIC(4,2) 2 dígitos 2 dígitos -99.99 a +99.99 NUMERIC(6,0) 6 dígitos 0 dígitos -999,999 a +999,999 NUMERIC(5,4) 1 dígito 4 dígitos -9.9999 a +9.9999 | E6: Variable (2 bytes por cada 4 dígitos + cabecera de 5 a 8 bytes) | F6: Valores monetarios exactos. Se usa NUMERIC(10,2) en precio, precio_unitario y total.
A7: =A6+1 -> 5 | B7: LÓGICO | C7: BOOLEAN | D7: 't' (o TRUE)/ 'f' (o FALSE) | E7: 1 | F7: Valores TRUE / FALSE. Usado en notificacion.leida.
A8: =A7+1 -> 6 | B8: TEXTO | C8: TEXT | D8: Hasta 1 GB | E8: Variable (1 o 4 bytes de cabecera + contenido) | F8: Texto sin límite de longitud. En este modelo los textos largos se limitan con VARCHAR(n) para conservar el tamaño definido en la tarea 2.
A9: =A8+1 -> 7 | B9: CARACTER | C9: CHAR(n) | D9: Exactamente n caracteres | E9: n (+ 1 byte de cabecera) | F9: Cadena de longitud fija, rellena con espacios. No se usa en este modelo.
A10: =A9+1 -> 8 | B10: FECHA | C10: DATE | D10: • Límite inferior: 4713 a. C. (Antes de Cristo / BC) • Límite superior: 5,874,897 d. C. (Después de Cristo / AD) | E10: 4 | F10: Solo fecha. Usado en evento.fecha.
A11: =A10+1 -> 9 | B11: FECHA_HORA | C11: TIMESTAMP | D11: • Límite Inferior: 4713 a. C. • Límite Superior: 294,276 d. C. • Precisión por defecto: 6 dígitos en los microsegundos. | E11: 8 | F11: Fecha y hora sin zona horaria. Usado en fechas de publicación, comentario, mensaje, venta, etc. Para solo hora se usa TIME (8 bytes), como en evento.hora.
A12: =A11+1 -> 10 | B12: IMAGEN | C12: BYTEA | D12: Límite Máximo Absoluto: Puede almacenar cadenas binarias de hasta 1 Gigabyte (GB) por celda. | E12: Variable (1 o 4 bytes de cabecera + contenido) | F12: No se usa: las imágenes se almacenan como URL (VARCHAR) y no como binario dentro de la base.
A13: =A12+1 -> 11 | B13: AUDIO | C13: BYTEA | D13: Límite Máximo Absoluto: Puede almacenar cadenas binarias de hasta 1 Gigabyte (GB) por celda. | E13: Variable (1 o 4 bytes de cabecera + contenido) | F13: No se usa en este modelo; los archivos de audio se referenciarían por URL.
A14: =A13+1 -> 12 | B14: URL | C14: VARCHAR(255) | D14: 255 caracteres. | E14: Variable (1 o 4 bytes de cabecera + longitud real) | F14: Usado en foto_perfil_url y contenido_multimedia.
A15: =A14+1 -> 13 | B15: ENUM | C15: CREATE TYPE … AS ENUM (…) | D15: el conjunto exacto de las etiquetas de texto que escribiste entre comillas dentro de los paréntesis durante su creación, más el valor NULL (a menos que se restrinja). | E15: 4 | F15: No se usa; el dominio de estado_publicacion (PUBLICADO, OCULTO, ELIMINADO) se define con VARCHAR(20) como en la tarea 2.
... A18: =A17+1 -> 16 | B18: JSON | C18: JSONB | D18: Límite Máximo Absoluto: puede pesar hasta 1 Gigabyte (GB) en su representación binaria. | E18: Variable (según el contenido) | F18: Datos semiestructurados indexables. No se usa en las tablas finales; JSON guarda el texto tal cual y JSONB lo almacena en binario.

Sheet DICCIONARIO DATOS (Físico)
A1: DICCIONARIO DE DATOS FÍSICO (PostgreSQL)
A2: Inventario de Tablas
A3: # | B3: Tabla | F3: Descripción Tabla | X3: Observaciones
A4: 1 | B4: ='Inventario Modelo Lógico (corre'!B3 -> usuario | F4: ='Inventario Modelo Lógico (corre'!C3 -> Persona registrada en la plataforma que interactúa con la red social. | X4: ='Inventario Modelo Lógico (corre'!D3 -> Origen: Entidad Usuario | PK: id_usuario | FK: id_rol, id_tipo_usuario | UK: nombre_usuario, correo
A5: =A4+1 -> 2 | B5: ='Inventario Modelo Lógico (corre'!B4 -> rol | F5: ='Inventario Modelo Lógico (corre'!C4 -> Clasifica a los usuarios según sus permisos y nivel de acceso dentro del sistema. | X5: ='Inventario Modelo Lógico (corre'!D4 -> Origen: Entidad Rol | PK: id_rol | UK: nombre_rol
A6: =A5+1 -> 3 | B6: ='Inventario Modelo Lógico (corre'!B5 -> tipo_usuario | F6: ='Inventario Modelo Lógico (corre'!C5 -> Clasificación académica o profesional del usuario con fines estadísticos. | X6: ='Inventario Modelo Lógico (corre'!D5 -> Origen: Entidad TipoUsuario | PK: id_tipo_usuario | UK: nombre_tipo
A7: =A6+1 -> 4 | B7: ='Inventario Modelo Lógico (corre'!B6 -> perfil | F7: ='Inventario Modelo Lógico (corre'!C6 -> Extensión de la información del usuario que almacena intereses, habilidades y datos adicionales en formato JSONB. | X7: ='Inventario Modelo Lógico (corre'!D6 -> Origen: Entidad Perfil (débil) | PK: id_perfil | FK: id_usuario | UK: id_usuario
A8: =A7+1 -> 5 | B8: ='Inventario Modelo Lógico (corre'!B7 -> interes | F8: ='Inventario Modelo Lógico (corre'!C7 -> Catálogo de intereses personales (fotografía, videojuegos, lectura, etc.) que los usuarios pueden asociar a su cuenta. | X8: ='Inventario Modelo Lógico (corre'!D7 -> Origen: Entidad Interes | PK: id_interes | UK: nombre_interes
A9: =A8+1 -> 6 | B9: ='Inventario Modelo Lógico (corre'!B8 -> habilidad | F9: ='Inventario Modelo Lógico (corre'!C8 -> Catálogo de habilidades (programación, diseño gráfico, etc.) que los usuarios pueden declarar en su cuenta. | X9: ='Inventario Modelo Lógico (corre'!D8 -> Origen: Entidad Habilidad | PK: id_habilidad | UK: nombre_habilidad
A10: =A9+1 -> 7 | B10: ='Inventario Modelo Lógico (corre'!B9 -> publicacion | F10: ='Inventario Modelo Lógico (corre'!C9 -> Contenido compartido por un usuario en el muro de la red social. | X10: ='Inventario Modelo Lógico (corre'!D9 -> Origen: Entidad Publicacion | PK: id_publicacion | FK: id_usuario
A11: =A10+1 -> 8 | B11: ='Inventario Modelo Lógico (corre'!B10 -> comentario | F11: ='Inventario Modelo Lógico (corre'!C10 -> Respuesta o reacción escrita que un usuario realiza sobre una publicación específica. | X11: ='Inventario Modelo Lógico (corre'!D10 -> Origen: Entidad Comentario (débil) | PK: id_comentario | FK: id_publicacion, id_usuario, id_comentario_padre
A12: =A11+1 -> 9 | B12: ='Inventario Modelo Lógico (corre'!B11 -> grupo | F12: ='Inventario Modelo Lógico (corre'!C11 -> Espacio colaborativo creado para reunir usuarios con intereses académicos, deportivos o de ocio en común. | X12: ='Inventario Modelo Lógico (corre'!D11 -> Origen: Entidad Grupo | PK: id_grupo | FK: id_usuario_creador
A13: =A12+1 -> 10 | B13: ='Inventario Modelo Lógico (corre'!B12 -> tipo_servicio | F13: ='Inventario Modelo Lógico (corre'!C12 -> Catálogo predefinido que clasifica los servicios ofrecidos (tutorías, reparaciones, asesorías, etc.). | X13: ='Inventario Modelo Lógico (corre'!D12 -> Origen: Entidad TipoServicio | PK: id_tipo_servicio | UK: nombre_tipo
A14: =A13+1 -> 11 | B14: ='Inventario Modelo Lógico (corre'!B13 -> servicio | F14: ='Inventario Modelo Lógico (corre'!C13 -> Oferta concreta que un usuario publica para brindar un servicio a otros, con precio y descripción. | X14: ='Inventario Modelo Lógico (corre'!D13 -> Origen: Entidad Servicio | PK: id_servicio | FK: id_tipo_servicio, id_usuario
A15: =A14+1 -> 12 | B15: ='Inventario Modelo Lógico (corre'!B14 -> tipo_producto | F15: ='Inventario Modelo Lógico (corre'!C14 -> Catálogo predefinido que clasifica los productos en venta (libros, tecnología, ropa, etc.). | X15: ='Inventario Modelo Lógico (corre'!D14 -> Origen: Entidad TipoProducto | PK: id_tipo_producto | UK: nombre_tipo
A16: =A15+1 -> 13 | B16: ='Inventario Modelo Lógico (corre'!B15 -> producto | F16: ='Inventario Modelo Lógico (corre'!C15 -> Artículo físico o digital que un usuario publica para vender o adquirir dentro de la plataforma. | X16: ='Inventario Modelo Lógico (corre'!D15 -> Origen: Entidad Producto | PK: id_producto | FK: id_tipo_producto, id_usuario
... A34: =A33+1 -> 31 | B34: ='Inventario Modelo Lógico (corre'!B33 -> venta_evento | F34: ='Inventario Modelo Lógico (corre'!C33 -> Detalle de los eventos incluidos en cada venta (por ejemplo, entradas), con la cantidad y el precio unitario. | X34: ='Inventario Modelo Lógico (corre'!D33 -> Origen: Relación M:N Venta — incluye — Evento | PK: id_venta_evento | FK: id_venta, id_evento | UK compuesta: (id_venta, id_evento)
A36: Tablas en Detalle
A38: 1 | B38: Tabla | C38: =B4 -> usuario | G38: Descripción Tabla | K38: =F4 -> Persona registrada en la plataforma que interactúa con la red social. | X38: Versión | Y38: 1.0
A39: # | B39: Campo | C39: Descripción Campo | G39: Tipo Dato (PostgreSQL) | K39: Tamaño / Longitud | O39: Nulo | R39: PK | T39: FK | V39: UK | X39: Nota/Comentarios
A40: 1 | B40: id_usuario | C40: Identificador numérico único y autoincrementable que distingue a cada usuario dentro del sistema. Es la llave primaria de la tabla. | G40: SERIAL | K40: 11 | O40: No | R40: S
A41: 2 | B41: id_rol | C41: Llave foránea que enlaza al usuario con el rol que determina sus permisos dentro del sistema. | G41: INTEGER | K41: 11 | O41: No | T41: S | X41: FK → rol(id_rol).
A42: 3 | B42: id_tipo_usuario | C42: Llave foránea que enlaza al usuario con su clasificación académica o profesional. | G42: INTEGER | K42: 11 | O42: No | T42: S | X42: FK → tipo_usuario(id_tipo_usuario).
A43: 4 | B43: nombre_completo | C43: Nombres y apellidos reales de la persona, utilizados para identificación personal en el perfil y en la interfaz de la red social. | G43: VARCHAR | K43: 80 | O43: No
A44: 5 | B44: nombre_usuario | C44: Alias público único (handle) que el usuario elige para ser identificado, mencionado y etiquetado dentro de la Red Social. | G44: VARCHAR | K44: 50 | O44: No | V44: S
A45: 6 | B45: correo | C45: Dirección de correo electrónico única asociada a la cuenta, utilizada como medio de contacto, recuperación de contraseña y para iniciar sesión en la plataforma. | G45: VARCHAR | K45: 100 | O45: No | V45: S
A46: 7 | B46: contraseña | C46: Clave de acceso personal del usuario; se almacena encriptada (hash) por motivos de seguridad y es obligatoria para la autenticación en el sistema. | G46: VARCHAR | K46: 50 | O46: No | X46: Se almacena cifrada (hash), nunca en texto plano.
A48: N
A49: NOTA: En las columnas PK, FK y UK debe colocar “S” solamente cuando aplique. En la columna “Nulo” coloque “No” en caso de que el campo debe estar valorizado
A51: 2 | B51: Tabla | C51: =B5 -> rol | G51: Descripción Tabla | K51: =F5 -> Clasifica a los usuarios según sus permisos y nivel de acceso dentro del sistema. | X51: Versión | Y51: 1.0
A52: # | B52: Campo | C52: Descripción Campo | G52: Tipo Dato (PostgreSQL) | K52: Tamaño / Longitud | O52: Nulo | R52: PK | T52: FK | V52: UK | X52: Nota/Comentarios
A53: 1 | B53: id_rol | C53: Identificador numérico único que distingue a cada tipo de rol dentro del sistema. Es la llave primaria de la tabla y se utiliza para referenciar el nivel de permisos de un usuario. | G53: SERIAL | K53: 11 | O53: No | R53: S
A54: 2 | B54: nombre_rol | C54: Nombre corto y único que identifica al rol (Administrador, Auxiliar, Miembro o Visitante). Sirve para clasificar rápidamente el nivel de acceso y responsabilidad en la plataforma. | G54: VARCHAR | K54: 30 | O54: No | V54: S
A55: 3 | B55: descripcion | C55: Texto explicativo que detalla las funciones, permisos y alcance de las acciones que puede realizar un usuario asignado a ese rol dentro de la Red Social. | G55: VARCHAR | K55: 255 | O55: Sí
A57: N
A59: 3 | B59: Tabla | C59: =B6 -> tipo_usuario | G59: Descripción Tabla | K59: =F6 -> Clasificación académica o profesional del usuario con fines estadísticos. | X59: Versión | Y59: 1.0
A60: # | B60: Campo | C60: Descripción Campo | G60: Tipo Dato (PostgreSQL) | K60: Tamaño / Longitud | O60: Nulo | R60: PK | T60: FK | V60: UK | X60: Nota/Comentarios
A61: 1 | B61: id_tipo_usuario | C61: Identificador numérico único para cada clasificación de usuario. | G61: SERIAL | K61: 11 | O61: No | R61: S
A62: 2 | B62: nombre_tipo | C62: Nombre corto de la clasificación (ej. "Estudiante", "Egresado"). Es único para evitar duplicados. | G62: VARCHAR | K62: 50 | O62: No | V62: S
A63: 3 | B63: descripcion | C63: Breve explicación de a quién pertenece ese tipo de usuario y su propósito en la red (ej. "Usuario activo de pregrado"). | G63: VARCHAR | K63: 255 | O63: Sí
A65: N
A67: 4 | B67: Tabla | C67: =B7 -> perfil | G67: Descripción Tabla | K67: =F7 -> Extensión de la información del usuario que almacena intereses, habilidades y datos adicionales en formato JSONB. | X67: Versión | Y67: 1.0
A68: # | B68: Campo | C68: Descripción Campo | G68: Tipo Dato (PostgreSQL) | K68: Tamaño / Longitud | O68: Nulo | R68: PK | T68: FK | V68: UK | X68: Nota/Comentarios
A69: 1 | B69: id_perfil | C69: Identificador único del perfil de usuario. | G69: SERIAL | K69: 11 | O69: No | R69: S
A70: 2 | B70: id_usuario | C70: Llave foránea que enlaza el perfil con su dueño. | G70: INTEGER | K70: 11 | O70: No | T70: S | V70: S | X70: Relación 1:1: FK único (UK) hacia el usuario dueño del perfil. FK → usuario(id_usuario).
A71: 3 | B71: foto_perfil_url | C71: Enlace (URL) a la imagen de perfil del usuario. | G71: VARCHAR | K71: 255 | O71: Sí
A72: 4 | B72: biografia | C72: Descripción personal corta que el usuario escribe para presentarse ante la comunidad. | G72: VARCHAR | K72: 500 | O72: Sí
A73: 5 | B73: fecha_actualizacion | C73: Fecha y hora de la última modificación realizada al perfil. Se actualiza automáticamente. | G73: TIMESTAMP | O73: No | X73: Se actualiza automáticamente en cada modificación.
A75: N
A77: 5 | B77: Tabla | C77: =B8 -> interes | G77: Descripción Tabla | K77: =F8 -> Catálogo de intereses personales (fotografía, videojuegos, lectura, etc.) que los usuarios pueden asociar a su cuenta. | X77: Versión | Y77: 1.0
A78: # | B78: Campo | C78: Descripción Campo | G78: Tipo Dato (PostgreSQL) | K78: Tamaño / Longitud | O78: Nulo | R78: PK | T78: FK | V78: UK | X78: Nota/Comentarios
A79: 1 | B79: id_interes | C79: Identificador único del interés. | G79: SERIAL | K79: 11 | O79: No | R79: S
A80: 2 | B80: nombre_interes | C80: Nombre del interés registrado (ej. Fotografía, Videojuegos, Lectura). | G80: VARCHAR | K80: 50 | O80: No | V80: S
A82: N
A84: 6 | B84: Tabla | C84: =B9 -> habilidad | G84: Descripción Tabla | K84: =F9 -> Catálogo de habilidades (programación, diseño gráfico, etc.) que los usuarios pueden declarar en su cuenta. | X84: Versión | Y84: 1.0
A85: # | B85: Campo | C85: Descripción Campo | G85: Tipo Dato (PostgreSQL) | K85: Tamaño / Longitud | O85: Nulo | R85: PK | T85: FK | V85: UK | X85: Nota/Comentarios
A86: 1 | B86: id_habilidad | C86: Identificador único de la habilidad. | G86: SERIAL | K86: 11 | O86: No | R86: S
A87: 2 | B87: nombre_habilidad | C87: Nombre de la habilidad registrada (ej. Programación, Diseño gráfico). | G87: VARCHAR | K87: 50 | O87: No | V87: S
A89: N
A91: 7 | B91: Tabla | C91: =B10 -> publicacion | G91: Descripción Tabla | K91: =F10 -> Contenido compartido por un usuario en el muro de la red social. | X91: Versión | Y91: 1.0
A92: # | B92: Campo | C92: Descripción Campo | G92: Tipo Dato (PostgreSQL) | K92: Tamaño / Longitud | O92: Nulo | R92: PK | T92: FK | V92: UK | X92: Nota/Comentarios
A93: 1 | B93: id_publicacion | C93: Identificador único para cada publicación realizada en la red social. | G93: SERIAL | K93: 11 | O93: No | R93: S
A94: 2 | B94: id_usuario | C94: Llave foránea que indica el autor de la publicación (quien la escribe). | G94: INTEGER | K94: 11 | O94: No | T94: S | X94: FK → usuario(id_usuario).
A95: 3 | B95: contenido_texto | C95: Cuerpo principal del mensaje, pregunta, noticia o meme que el usuario quiere compartir. | G95: VARCHAR | K95: 1000 | O95: Sí
A96: 4 | B96: contenido_multimedia | C96: Enlace (URL) opcional a imágenes, videos o documentos adjuntos a la publicación. | G96: VARCHAR | K96: 255 | O96: Sí
A97: 5 | B97: fecha_hora_publicacion | C97: Momento exacto en que se publicó el contenido (por defecto, la fecha y hora actual). | G97: TIMESTAMP | O97: No | X97: Valor por defecto: fecha y hora actual.
A98: 6 | B98: estado_publicacion | C98: Controla la visibilidad: PUBLICADO, OCULTO (por el usuario) o ELIMINADO (por moderación). | G98: VARCHAR | K98: 20 | O98: No | X98: Dominio: PUBLICADO, OCULTO, ELIMINADO.
A100: N
A102: 8 | B102: Tabla | C102: =B11 -> comentario | G102: Descripción Tabla | K102: =F11 -> Respuesta o reacción escrita que un usuario realiza sobre una publicación específica. | X102: Versión | Y102: 1.0
A103: # | B103: Campo | C103: Descripción Campo | G103: Tipo Dato (PostgreSQL) | K103: Tamaño / Longitud | O103: Nulo | R103: PK | T103: FK | V103: UK | X103: Nota/Comentarios
A104: 1 | B104: id_comentario | C104: Identificador único para cada comentario realizado en una publicación. | G104: SERIAL | K104: 11 | O104: No | R104: S
A105: 2 | B105: id_publicacion | C105: Llave foránea que indica a qué publicación pertenece este comentario. | G105: INTEGER | K105: 11 | O105: No | T105: S | X105: FK → publicacion(id_publicacion).
A106: 3 | B106: id_usuario | C106: Llave foránea que indica el autor del comentario (diferente al de la publicación). | G106: INTEGER | K106: 11 | O106: No | T106: S | X106: FK → usuario(id_usuario).
A107: 4 | B107: contenido_comentario | C107: Texto escrito por el usuario como respuesta, opinión o aporte sobre la publicación. | G107: VARCHAR | K107: 500 | O107: No
A108: 5 | B108: fecha_hora_comentario | C108: Fecha y hora exacta en que se dejó el comentario (por defecto, la actual). | G108: TIMESTAMP | O108: No | X108: Valor por defecto: fecha y hora actual.
A109: 6 | B109: id_comentario_padre | C109: Permite responder a un comentario específico (autorreferencia a la misma tabla). | G109: INTEGER | K109: 11 | O109: Sí | T109: S | X109: Autorreferencia: FK hacia id_comentario de la misma tabla.
A111: N
A113: 9 | B113: Tabla | C113: =B12 -> grupo | G113: Descripción Tabla | K113: =F12 -> Espacio colaborativo creado para reunir usuarios con intereses académicos, deportivos o de ocio en común. | X113: Versión | Y113: 1.0
A114: # | B114: Campo | C114: Descripción Campo | G114: Tipo Dato (PostgreSQL) | K114: Tamaño / Longitud | O114: Nulo | R114: PK | T114: FK | V114: UK | X114: Nota/Comentarios
A115: 1 | B115: id_grupo | C115: Identificador único de la comunidad o equipo. | G115: SERIAL | K115: 11 | O115: No | R115: S
A116: 2 | B116: id_usuario_creador | C116: Usuario participante que fundó o administra el grupo. | G116: INTEGER | K116: 11 | O116: No | T116: S | X116: FK → usuario(id_usuario).
A117: 3 | B117: nombre_grupo | C117: Nombre público de la agrupación (Equipo de Hackatón, Club de videojuegos). | G117: VARCHAR | K117: 80 | O117: No
A119: N
A121: 10 | B121: Tabla | C121: =B13 -> tipo_servicio | G121: Descripción Tabla | K121: =F13 -> Catálogo predefinido que clasifica los servicios ofrecidos (tutorías, reparaciones, asesorías, etc.). | X121: Versión | Y121: 1.0
A122: # | B122: Campo | C122: Descripción Campo | G122: Tipo Dato (PostgreSQL) | K122: Tamaño / Longitud | O122: Nulo | R122: PK | T122: FK | V122: UK | X122: Nota/Comentarios
A123: 1 | B123: id_tipo_servicio | C123: Código único de la categoría del servicio. | G123: SERIAL | K123: 11 | O123: No | R123: S
A124: 2 | B124: nombre_tipo | C124: Clasificación amplia del servicio (Cambalache, Tutoría, Cursos). | G124: VARCHAR | K124: 50 | O124: No | V124: S
A125: 3 | B125: descripcion | C125: Detalle explícito de las características del tipo de oferta. | G125: VARCHAR | K125: 255 | O125: Sí
A127: N
A129: 11 | B129: Tabla | C129: =B14 -> servicio | G129: Descripción Tabla | K129: =F14 -> Oferta concreta que un usuario publica para brindar un servicio a otros, con precio y descripción. | X129: Versión | Y129: 1.0
A130: # | B130: Campo | C130: Descripción Campo | G130: Tipo Dato (PostgreSQL) | K130: Tamaño / Longitud | O130: Nulo | R130: PK | T130: FK | V130: UK | X130: Nota/Comentarios
A131: 1 | B131: id_servicio | C131: Identificador único del servicio publicado. | G131: SERIAL | K131: 11 | O131: No | R131: S
A132: 2 | B132: id_tipo_servicio | C132: Categoría a la que pertenece el servicio. | G132: INTEGER | K132: 11 | O132: No | T132: S | X132: FK → tipo_servicio(id_tipo_servicio).
A133: 3 | B133: id_usuario | C133: Usuario participante que promociona o presta el servicio. | G133: INTEGER | K133: 11 | O133: No | T133: S | X133: FK → usuario(id_usuario).
A134: 4 | B134: precio | C134: Tarifa monetaria, tasa o modalidad de intercambio solicitada. | G134: NUMERIC | K134: 10,2 | O134: Sí
A136: N
A138: 12 | B138: Tabla | C138: =B15 -> tipo_producto | G138: Descripción Tabla | K138: =F15 -> Catálogo predefinido que clasifica los productos en venta (libros, tecnología, ropa, etc.). | X138: Versión | Y138: 1.0
A139: # | B139: Campo | C139: Descripción Campo | G139: Tipo Dato (PostgreSQL) | K139: Tamaño / Longitud | O139: Nulo | R139: PK | T139: FK | V139: UK | X139: Nota/Comentarios
A140: 1 | B140: id_tipo_producto | C140: Código único de la categoría de producto. | G140: SERIAL | K140: 11 | O140: No | R140: S
A141: 2 | B141: nombre_tipo | C141: Clasificación del bien físico o digital (Libros, Ropa, Vehículos). | G141: VARCHAR | K141: 50 | O141: No | V141: S
...
